gengineapi/__init__.py
gengineapi/client.py
gengineapi/config.py
gengineapi/exceptions.py
gengineapi/farm.py
gengineapi/http.py
gengineapi/modules/__init__.py
gengineapi/modules/auth.py
gengineapi/modules/base.py
gengineapi/modules/currencies.py
gengineapi/modules/finances.py
gengineapi/modules/payments.py
gengineapi/modules/transactions.py
gengineapi/modules/users.py
gengineapi-0.2.2.dist-info/METADATA
gengineapi-0.2.2.dist-info/WHEEL
gengineapi-0.2.2.dist-info/top_level.txt
gengineapi-0.2.2.dist-info/RECORD
