Metadata-Version: 2.4
Name: gengineapi
Version: 0.2.2
Summary: G-Engine API Client
Requires-Python: >=3.13
Requires-Dist: aiohttp>=3.8.0
Requires-Dist: typing-extensions>=4.0.0
Requires-Dist: aiohttp-socks>=0.7.1
